todoapp/__init__.py
todoapp/todo.py
todoapp_CLI-0.1.0.dist-info/LICENSE
todoapp_CLI-0.1.0.dist-info/METADATA
todoapp_CLI-0.1.0.dist-info/WHEEL
todoapp_CLI-0.1.0.dist-info/entry_points.txt
todoapp_CLI-0.1.0.dist-info/top_level.txt
todoapp_CLI-0.1.0.dist-info/RECORD
